[{"id":1,"first_name":"Wendy","last_name":"Moorcraft","email":"wmoorcraft0@time.com"},
{"id":2,"first_name":"Gard","last_name":"Lergan","email":"glergan1@yandex.ru"},
{"id":3,"first_name":"Janaya","last_name":"Blacker","email":"jblacker2@freewebs.com"},
{"id":4,"first_name":"Joan","last_name":"Adiscot","email":"jadiscot3@4shared.com"},
{"id":5,"first_name":"Fianna","last_name":"Farfoot","email":"ffarfoot4@noaa.gov"},
{"id":6,"first_name":"Cathryn","last_name":"McGann","email":"cmcgann5@abc.net.au"},
{"id":7,"first_name":"Ezechiel","last_name":"Strain","email":"estrain6@google.nl"},
{"id":8,"first_name":"Dagny","last_name":"Othen","email":"dothen7@wiley.com"},
{"id":9,"first_name":"Ermentrude","last_name":"Milburne","email":"emilburne8@addtoany.com"},
{"id":10,"first_name":"Cally","last_name":"Jearum","email":"cjearum9@epa.gov"},
{"id":11,"first_name":"Vinnie","last_name":"Seligson","email":"vseligsona@linkedin.com"},
{"id":12,"first_name":"Christine","last_name":"Croser","email":"ccroserb@berkeley.edu"},
{"id":13,"first_name":"Cosmo","last_name":"Cassy","email":"ccassyc@google.es"},
{"id":14,"first_name":"Wynnie","last_name":"Dryden","email":"wdrydend@dot.gov"},
{"id":15,"first_name":"Bone","last_name":"McComiskey","email":"bmccomiskeye@oracle.com"},
{"id":16,"first_name":"Silvana","last_name":"Vanshin","email":"svanshinf@is.gd"},
{"id":17,"first_name":"Lothario","last_name":"McGeachie","email":"lmcgeachieg@msn.com"},
{"id":18,"first_name":"Ileane","last_name":"O' Neligan","email":"ioneliganh@fc2.com"},
{"id":19,"first_name":"Adiana","last_name":"Sprowson","email":"asprowsoni@networkadvertising.org"},
{"id":20,"first_name":"Esdras","last_name":"Barsam","email":"ebarsamj@photobucket.com"}]